README.md
setup.py
ktdparser/__init__.py
ktdparser/config.py
ktdparser/db.py
ktdparser/parser.py
ktdparser.egg-info/PKG-INFO
ktdparser.egg-info/SOURCES.txt
ktdparser.egg-info/dependency_links.txt
ktdparser.egg-info/requires.txt
ktdparser.egg-info/top_level.txt