Metadata-Version: 2.1
Name: ktdparser
Version: 0.0.1
Summary: PDF parser for special forms using Tabula.
Requires-Python: >=3.10
Requires-Dist: tabula-py
Requires-Dist: PyPDF2
Requires-Dist: tqdm
Requires-Dist: psycopg2-binary
Requires-Dist: openpyxl
Requires-Dist: pandas
